datadict/__init__.py
datadict/datadict.py
datadict/jupyter/__init__.py
datadict/jupyter/jupyter.py
pandas_datadict-0.2.3.dist-info/LICENSE
pandas_datadict-0.2.3.dist-info/METADATA
pandas_datadict-0.2.3.dist-info/WHEEL
pandas_datadict-0.2.3.dist-info/top_level.txt
pandas_datadict-0.2.3.dist-info/RECORD
