Metadata-Version: 2.1
Name: pandas-datadict
Version: 0.2.3
Summary: Data dictionary functionality for pandas data frames
Home-page: https://github.com/177arc/pandas-datadict
Author: Marc Maier
Author-email: py@177arc.net
License: MIT
Platform: UNKNOWN
Classifier: License :: OSI Approved :: MIT License
Classifier: Programming Language :: Python :: 3
Classifier: Programming Language :: Python :: 3.6
Classifier: Programming Language :: Python :: 3.7
Requires-Dist: pandas (>=0.19)
Requires-Dist: openpyxl
